jl95/batteries/__init__.py
"jl95/batteries/argparse/__init__,py"
jl95/batteries/argparse/ext/__init__.py
jl95/batteries/os/__init__.py
jl95/batteries/signal/__init__.py
jl95/batteries/sys/__init__.py
jl95terceira/batteries/__init__.py
jl95terceira/batteries/os/__init__.py
jl95terceira/batteries/signal/__init__.py
jl95terceira/batteries/sys/__init__.py
jl95terceira_batteries-1.8.0.dist-info/METADATA
jl95terceira_batteries-1.8.0.dist-info/WHEEL
jl95terceira_batteries-1.8.0.dist-info/RECORD
