Metadata-Version: 2.4
Name: jl95terceira_batteries
Version: 1.8.0
Summary: Batteries to complement the standard library
Project-URL: Homepage, https://github.com/jl95terceira/batteries-python
Project-URL: Issues, https://github.com/jl95terceira/batteries-python/issues
Author-email: Joao Luis Ornelas da Silva <jl95terceira@gmail.com>
Classifier: License :: OSI Approved :: MIT License
Classifier: Operating System :: OS Independent
Classifier: Programming Language :: Python :: 3
Requires-Python: >=3.12
